wres/explorer/__init__.py
wres/explorer/_version.py
wres/explorer/callbacks.py
wres/explorer/cli.py
wres/explorer/dashboard.py
wres/explorer/data.py
wres/explorer/images.py
wres/explorer/layout.py
wres/explorer/plots.py
wres/explorer/widgets.py
wres_explorer-0.5.0.dist-info/licenses/LICENSE
wres_explorer-0.5.0.dist-info/licenses/NOTICE
wres_explorer-0.5.0.dist-info/METADATA
wres_explorer-0.5.0.dist-info/WHEEL
wres_explorer-0.5.0.dist-info/entry_points.txt
wres_explorer-0.5.0.dist-info/top_level.txt
wres_explorer-0.5.0.dist-info/RECORD
